shinu-0.0.2.dist-info/METADATA
shinu-0.0.2.dist-info/WHEEL
shinu.libs/libgcc_s-1e52349c.so.1
shinu/__init__.py
shinu/shinu.abi3.so
shinu-0.0.2.dist-info/RECORD
