Metadata-Version: 2.4
Name: shinu
Version: 0.0.2
Classifier: Development Status :: 4 - Beta
Classifier: Intended Audience :: Developers
Classifier: License :: OSI Approved :: MIT License
Classifier: Operating System :: OS Independent
Classifier: Programming Language :: Python :: 3.10
Classifier: Programming Language :: Python :: 3.11
Classifier: Programming Language :: Python :: 3.12
Classifier: Programming Language :: Python :: 3.13
Classifier: Programming Language :: Rust
Classifier: Topic :: Multimedia :: Graphics
Classifier: Topic :: Multimedia :: Sound/Audio
Classifier: Topic :: Multimedia :: Video
Provides-Extra: image
Provides-Extra: video
Provides-Extra: audio
Provides-Extra: pdf
Summary: High-performance Rust-based media compression for Python and FastAPI
Author-email: Swapnil Jagadale <swapnilwork999@gmail.com>
Requires-Python: >=3.10
